codedharmony_ai_models/azure_connector.py
codedharmony_ai_models/init.py
codedharmony_ai_models/openai_connector.py
codedharmony_ai_models/utils.py
codedharmony_ai_models-0.1.3.dist-info/LICENSE
codedharmony_ai_models-0.1.3.dist-info/METADATA
codedharmony_ai_models-0.1.3.dist-info/WHEEL
codedharmony_ai_models-0.1.3.dist-info/top_level.txt
codedharmony_ai_models-0.1.3.dist-info/RECORD
