Metadata-Version: 2.2
Name: codedharmony-ai-models
Version: 0.1.3
Summary: A package to manage connections to AI model services such as OpenAI and Azure OpenAI.
Author-email: Andrew Vialichka <andreivialichka@onlineimmigrant.com>
License: MIT License
Keywords: ai,openai,azure,models,sdk
Classifier: Development Status :: 3 - Alpha
Classifier: Intended Audience :: Developers
Classifier: Programming Language :: Python :: 3
Classifier: License :: OSI Approved :: MIT License
License-File: LICENSE
Requires-Dist: openai>=1.0.0
